stockpy/__init__.py
stockpy/base.py
stockpy/exceptions.py
stockpy/history.py
stockpy/callbacks/__init__.py
stockpy/callbacks/_base.py
stockpy/callbacks/_logging.py
stockpy/callbacks/_lr_scheduler.py
stockpy/callbacks/_regularization.py
stockpy/callbacks/_scoring.py
stockpy/callbacks/_training.py
stockpy/neural_network/__init__.py
stockpy/neural_network/_bigru.py
stockpy/neural_network/_bilstm.py
stockpy/neural_network/_cnn.py
stockpy/neural_network/_gru.py
stockpy/neural_network/_lstm.py
stockpy/neural_network/_mlp.py
stockpy/preprocessing/__init__.py
stockpy/preprocessing/_base.py
stockpy/preprocessing/_dataset.py
stockpy/probabilistic/__init__.py
stockpy/probabilistic/_bcnn.py
stockpy/probabilistic/_bnn.py
stockpy/probabilistic/_combiner.py
stockpy/probabilistic/_dmm.py
stockpy/probabilistic/_emitter.py
stockpy/probabilistic/_nhmm.py
stockpy/probabilistic/_transition.py
stockpy/utils/__init__.py
stockpy/utils/_utils.py
stockpy_learn-0.3.2.dist-info/LICENSE
stockpy_learn-0.3.2.dist-info/METADATA
stockpy_learn-0.3.2.dist-info/WHEEL
stockpy_learn-0.3.2.dist-info/top_level.txt
stockpy_learn-0.3.2.dist-info/RECORD
