Metadata-Version: 2.1
Name: stockpy-learn
Version: 0.3.2
Summary: Deep Learning Regression and Classification Library built on top of PyTorch and Pyro
Home-page: https://github.com/SilvioBaratto/stockpy
Author: Silvio Baratto
Author-email: silvio.baratto22@gmail.com
License: MIT License
Classifier: Intended Audience :: Developers
Classifier: License :: OSI Approved :: MIT License
Classifier: Operating System :: OS Independent
Classifier: Programming Language :: Python :: 3
Classifier: Intended Audience :: Science/Research
Classifier: Topic :: Scientific/Engineering :: Mathematics
Requires-Python: >=3.8
License-File: LICENSE
Requires-Dist: torch (>=1.9.1)
Requires-Dist: pyro-ppl (>=1.7.0)
Requires-Dist: numpy (>=1.21.2)
Requires-Dist: pandas (>=1.3.3)
Requires-Dist: tqdm (==4.62.3)
Requires-Dist: jupyter
Requires-Dist: matplotlib (>=2.0.2)
Requires-Dist: pandas
Requires-Dist: pillow
Requires-Dist: scikit-learn (>=0.24.2)
Requires-Dist: safetensors (>=0.3.1)
Requires-Dist: sphinx
Requires-Dist: sphinx-rtd-theme
Provides-Extra: docs
Requires-Dist: Sphinx ; extra == 'docs'
Requires-Dist: sphinx-rtd-theme ; extra == 'docs'
Requires-Dist: numpydoc ; extra == 'docs'
